stactools/datacube/__init__.py
stactools/datacube/commands.py
stactools/datacube/stac.py
stactools_datacube-0.0.1.dist-info/LICENSE
stactools_datacube-0.0.1.dist-info/METADATA
stactools_datacube-0.0.1.dist-info/WHEEL
stactools_datacube-0.0.1.dist-info/top_level.txt
stactools_datacube-0.0.1.dist-info/RECORD
