Metadata-Version: 2.1
Name: stactools-datacube
Version: 0.0.1
Summary: PROVIDE DESCRIPTION HERE
Home-page: https://github.com/stactools-packages/datacube
Author: stac-utils
Author-email: stac@radiant.earth
Project-URL: Issues, https://github.com/stactools-packages/datacube/issues
Keywords: stactools,pystac,catalog,STAC
Classifier: Development Status :: 4 - Beta
Classifier: License :: OSI Approved :: Apache Software License
Classifier: Programming Language :: Python :: 3.8
Classifier: Programming Language :: Python :: 3.9
Classifier: Programming Language :: Python :: 3.10
License-File: LICENSE
Requires-Dist: stactools (>=0.4.0)
Requires-Dist: gdal (>=3.3)
